dagent_llm/__init__.py
dagent_llm/cli.py
dagent_llm/keywords.py
dagent_llm/llm.py
dagent_llm/utils.py
dagent_llm/version.py
dagent_llm-0.2.9.dist-info/LICENSE
dagent_llm-0.2.9.dist-info/METADATA
dagent_llm-0.2.9.dist-info/WHEEL
dagent_llm-0.2.9.dist-info/entry_points.txt
dagent_llm-0.2.9.dist-info/top_level.txt
dagent_llm-0.2.9.dist-info/RECORD
