Metadata-Version: 2.1
Name: dagent_llm
Version: 0.2.9
Summary: A package for LLM operations.
Home-page: https://gitee.com/iint/dagent_llm
Author: Zhao Sheng
Author-email: zhaosheng@nuaa.edu.cn
Classifier: Programming Language :: Python :: 3
Classifier: License :: OSI Approved :: MIT License
Classifier: Operating System :: OS Independent
Requires-Python: >=3.10
License-File: LICENSE
Requires-Dist: dsqlenv
Requires-Dist: langchain-core >=0.3.10
Requires-Dist: langchain-openai >=0.2.2
Requires-Dist: rich >=13.8.0
Requires-Dist: pydantic >=2.10.2
Requires-Dist: pydantic-core >=2.27.1
Requires-Dist: pymysql >=1.0.2
Requires-Dist: pycryptodome >=3.10.0
